delft_physics_lab/__init__.py
delft_physics_lab/utils.py
delft_physics_lab/tests/__init__.py
delft_physics_lab/tests/test1.py
delft_physics_lab/tests/test2.py
delft_physics_lab/tests/test3.py
delft_physics_lab-0.14.dist-info/LICENSE
delft_physics_lab-0.14.dist-info/METADATA
delft_physics_lab-0.14.dist-info/WHEEL
delft_physics_lab-0.14.dist-info/top_level.txt
delft_physics_lab-0.14.dist-info/RECORD
