Metadata-Version: 2.1
Name: delft-physics-lab
Version: 0.14
Summary: delft physics lab
Home-page: UNKNOWN
License: MIT
Platform: UNKNOWN
License-File: LICENSE
Requires-Dist: numpy
Requires-Dist: scipy
Requires-Dist: matplotlib
Requires-Dist: tensorflow
